dj_rest_tickets/__init__.py
dj_rest_tickets/asgi.py
dj_rest_tickets/settings.py
dj_rest_tickets/tickets/__init__.py
dj_rest_tickets/tickets/admin.py
dj_rest_tickets/tickets/apps.py
dj_rest_tickets/tickets/migrations/0001_initial.py
dj_rest_tickets/tickets/migrations/__init__.py
dj_rest_tickets/tickets/models.py
dj_rest_tickets/tickets/permissions.py
dj_rest_tickets/tickets/serializers.py
dj_rest_tickets/tickets/tests.py
dj_rest_tickets/tickets/urls.py
dj_rest_tickets/tickets/views.py
dj_rest_tickets/urls.py
dj_rest_tickets/utils.py
dj_rest_tickets/wsgi.py
dj_rest_tickets-0.0.20.dist-info/METADATA
dj_rest_tickets-0.0.20.dist-info/WHEEL
dj_rest_tickets-0.0.20.dist-info/RECORD
