Metadata-Version: 2.3
Name: dj-rest-tickets
Version: 0.0.20
Summary: Mini ticket management system
Author: Aymane Nahji
Author-email: aymanenahjidev@gmail.com
Requires-Python: >=3.12
Classifier: Programming Language :: Python :: 3
Classifier: Programming Language :: Python :: 3.12
Classifier: Programming Language :: Python :: 3.13
Requires-Dist: django (==5.1.1)
Requires-Dist: django-cors-headers (==4.4.0)
Requires-Dist: django-filter (==24.3)
Requires-Dist: djangorestframework (==3.15.2)
